{
	"animations": [
		{
			"loop": false,
			"offsets": [
				0,
				0
			],
			"anim": "idle",
			"fps": 24,
			"name": "Idle",
			"indices": []
		},
		{
			"loop": false,
			"offsets": [
				130,
				-92
			],
			"anim": "left",
			"fps": 24,
			"name": "Left",
			"indices": []
		},
		{
			"loop": false,
			"offsets": [
				28,
				-79
			],
			"anim": "right",
			"fps": 24,
			"name": "Right",
			"indices": []
		},
		{
			"loop": false,
			"offsets": [
				63,
				-79
			],
			"anim": "down",
			"fps": 24,
			"name": "Down",
			"indices": []
		},
		{
			"loop": false,
			"offsets": [
				93,
				55
			],
			"anim": "up",
			"fps": 24,
			"name": "Up",
			"indices": []
		},
		{
			"offsets": [
				0,
				0
			],
			"indices": [],
			"fps": 24,
			"anim": "soupup",
			"loop": false,
			"name": "SoupUp"
		},
		{
			"offsets": [
				0,
				0
			],
			"indices": [],
			"fps": 24,
			"anim": "soupdown",
			"loop": false,
			"name": "SoupDown"
		},
		{
			"offsets": [
				0,
				0
			],
			"indices": [],
			"fps": 24,
			"anim": "soupright",
			"loop": false,
			"name": "SoupRIght"
		},
		{
			"offsets": [
				0,
				0
			],
			"indices": [],
			"fps": 24,
			"anim": "soupleft",
			"loop": false,
			"name": "SoupLeft"
		}
	],
	"no_antialiasing": false,
	"image": "characters/Tord-FLA",
	"position": [
		-360,
		290
	],
	"healthicon": "bf",
	"flip_x": false,
	"healthbar_colors": [
		49,
		176,
		209
	],
	"camera_position": [
		0,
		0
	],
	"sing_duration": 4,
	"scale": 1
}